Metadata-Version: 2.4
Name: django-honeypot-admin
Version: 2.0.0
Summary: A fake Django admin login screen to notify admins of attempted unauthorized access. Compatible with latest Django versions.
Home-page: https://github.com/Alien501/django-admin-honeypot
Download-URL: https://github.com/Alien501/django-admin-honeypot/tarball/v2.0.0
Author: Derek Payton
Author-email: derek.payton@gmail.com
Maintainer: Vignesh (Alien501)
Maintainer-email: cvignesh404@gmail.com
License: MIT License
Keywords: django admin honeypot trap security
Classifier: Development Status :: 5 - Production/Stable
Classifier: Framework :: Django
Classifier: Framework :: Django :: 3.2
Classifier: Framework :: Django :: 4.0
Classifier: Framework :: Django :: 4.1
Classifier: Framework :: Django :: 4.2
Classifier: Framework :: Django :: 5.0
Classifier: Framework :: Django :: 5.1
Classifier: Framework :: Django :: 5.2
Classifier: Intended Audience :: Developers
Classifier: License :: OSI Approved :: MIT License
Classifier: Natural Language :: English
Classifier: Operating System :: OS Independent
Classifier: Programming Language :: Python
Classifier: Programming Language :: Python :: 3
Classifier: Programming Language :: Python :: 3.8
Classifier: Programming Language :: Python :: 3.9
Classifier: Programming Language :: Python :: 3.10
Classifier: Programming Language :: Python :: 3.11
Classifier: Programming Language :: Python :: 3.12
Classifier: Topic :: Internet :: WWW/HTTP :: Dynamic Content
License-File: LICENSE
Requires-Dist: django>=3.2
Requires-Dist: django-ipware
Dynamic: author
Dynamic: author-email
Dynamic: classifier
Dynamic: description
Dynamic: download-url
Dynamic: home-page
Dynamic: keywords
Dynamic: license
Dynamic: license-file
Dynamic: maintainer
Dynamic: maintainer-email
Dynamic: requires-dist
Dynamic: summary
